README.md
setup.cfg
setup.py
krakenio/__init__.py
krakenio3.egg-info/PKG-INFO
krakenio3.egg-info/SOURCES.txt
krakenio3.egg-info/dependency_links.txt
krakenio3.egg-info/requires.txt
krakenio3.egg-info/top_level.txt